{
  "users": [
    {
      "id": 1,
      "names": "Jhayro Jhordan",
      "lastnames": "Roncal Tacilla",
      "email": "jhayro2017@gmail.com",
      "rol": "Mayorista",
      "password": "jhayro159"
    },
    {
      "id": 2,
      "names": "weqweqw",
      "lastnames": "eqwe",
      "email": "ewqewq@gmail.com",
      "rol": "Mayorista",
      "password": "wqewqewqe"
    },
    {
      "id": 3,
      "names": "Irwin",
      "lastnames": "Roncal",
      "email": "irwin159@gmail.com",
      "rol": "Mayorista",
      "password": "Irwin159"
    },
    {
      "id": 4,
      "names": "Pedro",
      "lastnames": "Tacilla",
      "email": "pedro159@gmail.com",
      "rol": "Agricultor",
      "password": "pedro159"
    },
    {
      "id": 5,
      "names": "Antony",
      "lastnames": "Ortega",
      "email": "xtreme@gmail.com",
      "rol": "Mayorista",
      "password": "123456789"
    }
  ],
  "products": [
    {
      "id": 4,
      "name": "choclo",
      "quantity": "150"
    },
    {
      "id": 5,
      "name": "papa2",
      "quantity": "30"
    },
    {
      "id": 6,
      "name": "Papa",
      "quantity": "50"
    }
  ]
}